yaml_creator/__init__.py
yaml_creator/resource_manager.py
yaml_creator-0.1.dist-info/METADATA
yaml_creator-0.1.dist-info/WHEEL
yaml_creator-0.1.dist-info/top_level.txt
yaml_creator-0.1.dist-info/RECORD
